devgraph_client/__init__.py
devgraph_client/api/__init__.py
devgraph_client/api/chat_completions/__init__.py
devgraph_client/api/chat_completions/create_chat_completions.py
devgraph_client/api/chats/__init__.py
devgraph_client/api/chats/create_chat.py
devgraph_client/api/chats/create_chat_suggestion.py
devgraph_client/api/chats/create_chat_title.py
devgraph_client/api/chats/delete_chat.py
devgraph_client/api/chats/delete_chat_suggestion.py
devgraph_client/api/chats/delete_chats_bulk.py
devgraph_client/api/chats/get_chat.py
devgraph_client/api/chats/get_chat_messages.py
devgraph_client/api/chats/get_chats.py
devgraph_client/api/chats/list_chat_suggestions.py
devgraph_client/api/chats/post_chat_messages.py
devgraph_client/api/chats/update_chat.py
devgraph_client/api/discovery/__init__.py
devgraph_client/api/discovery/create_configured_provider.py
devgraph_client/api/discovery/delete_configured_provider.py
devgraph_client/api/discovery/get_all_provider_versions.py
devgraph_client/api/discovery/get_configured_provider.py
devgraph_client/api/discovery/get_deprecated_provider_configs.py
devgraph_client/api/discovery/get_discovery_provider_config_schema.py
devgraph_client/api/discovery/list_configured_providers.py
devgraph_client/api/discovery/list_discovery_providers.py
devgraph_client/api/discovery/migrate_all_deprecated_configs.py
devgraph_client/api/discovery/migrate_provider_config.py
devgraph_client/api/discovery/update_configured_provider.py
devgraph_client/api/entities/__init__.py
devgraph_client/api/entities/cleanup_orphaned_entities.py
devgraph_client/api/entities/create_entities_bulk.py
devgraph_client/api/entities/create_entity.py
devgraph_client/api/entities/create_entity_definition.py
devgraph_client/api/entities/create_entity_relation.py
devgraph_client/api/entities/create_entity_relations_bulk.py
devgraph_client/api/entities/delete_entity.py
devgraph_client/api/entities/delete_entity_definition.py
devgraph_client/api/entities/delete_entity_relation.py
devgraph_client-1.0.0b19.dist-info/LICENSE
devgraph_client-1.0.0b19.dist-info/METADATA
devgraph_client-1.0.0b19.dist-info/WHEEL
devgraph_client-1.0.0b19.dist-info/RECORD
